encdec8b10b/__init__.py
encdec8b10b/core.py
encdec_8b10b/__init__.py
encdec_8b10b/encdec_8b10b.py
tests/__init__.py
tests/context.py
tests/test_suite.py
encdec8b10b-1.0.dist-info/LICENSE
encdec8b10b-1.0.dist-info/METADATA
encdec8b10b-1.0.dist-info/WHEEL
encdec8b10b-1.0.dist-info/top_level.txt
encdec8b10b-1.0.dist-info/RECORD
