Metadata-Version: 2.1
Name: encdec8b10b
Version: 1.0
Summary: 8B10B Encoding and Decoding
Home-page: https://github.com/olagrottvik/encdec8b10b
Author: Ola Grøttvik
Author-email: olagrottvik@gmail.com
License: MIT
Platform: UNKNOWN
